airflow/providers/mnb/__init__.py
airflow/providers/mnb/hooks/__init__.py
airflow/providers/mnb/hooks/mnb.py
airflow/providers/mnb/operators/__init__.py
airflow/providers/mnb/operators/mnb.py
airflow/providers/mnb/sensors/__init__.py
airflow/providers/mnb/sensors/mnb.py
apache_airflow_providers_mnb-1.0.2.dist-info/METADATA
apache_airflow_providers_mnb-1.0.2.dist-info/WHEEL
apache_airflow_providers_mnb-1.0.2.dist-info/entry_points.txt
apache_airflow_providers_mnb-1.0.2.dist-info/LICENSE.md
apache_airflow_providers_mnb-1.0.2.dist-info/RECORD
