Metadata-Version: 2.1
Name: apache-airflow-providers-mnb
Version: 1.0.2
Summary: Provider for Apache Airflow. Implements apache-airflow-providers-mnb package
Home-page: https://github.com/belidzs/apache-airflow-providers-mnb
License: MIT
Author: Balázs Keresztury
Author-email: balazs@keresztury.com
Requires-Python: >=3.8.1,<4.0.0
Classifier: Framework :: Apache Airflow
Classifier: Framework :: Apache Airflow :: Provider
Classifier: License :: OSI Approved :: MIT License
Classifier: Programming Language :: Python :: 3
Classifier: Programming Language :: Python :: 3.9
Classifier: Programming Language :: Python :: 3.10
Classifier: Programming Language :: Python :: 3.11
Requires-Dist: apache-airflow (>=2.0,<3.0)
Requires-Dist: mnb (>=1.0.0,<2.0.0)
Requires-Dist: zeep (>=4.2,<5.0)
Project-URL: Repository, https://github.com/belidzs/apache-airflow-providers-mnb
